auth0_component_prime/DS_Store
auth0_component_prime/__init__.py
auth0_component_prime/frontend/dist/index.html
auth0_component_prime/frontend/dist/vite.svg
auth0_component_prime/frontend/dist/assets/index.5223bee9.css
auth0_component_prime/frontend/dist/assets/index.9a5fd6ad.js
streamlit_auth0_component_prime-1.1.dist-info/LICENSE
streamlit_auth0_component_prime-1.1.dist-info/METADATA
streamlit_auth0_component_prime-1.1.dist-info/WHEEL
streamlit_auth0_component_prime-1.1.dist-info/top_level.txt
streamlit_auth0_component_prime-1.1.dist-info/RECORD
