Metadata-Version: 2.1
Name: streamlit-auth0-component-prime
Version: 1.1
Home-page: 
Author: 
Author-email: 
Requires-Python: >=3.8
License-File: LICENSE
Requires-Dist: streamlit >=0.63
Requires-Dist: python-jose ==3.3.0
